{
  "city": "Miami",
  "country": "USA",
  "venue": "Hard Rock Stadium",
  "capacity": 65326,
  "matches_hosted": 6,
  "date": "2026-06-15",
  "date_type": "match",
  "url": "https://www.booking.com/searchresults.html?ss=Miami Gardens, Florida&checkin=2026-06-15&checkout=2026-06-16&group_adults=2&no_rooms=1&nflt=class%3D3%3Bclass%3D4%3Bclass%3D5&order=price",
  "prices_found": [
    92.0,
    92.0,
    130.0,
    130.0,
    137.0,
    137.0,
    140.0,
    140.0,
    144.0,
    144.0,
    144.0,
    144.0,
    149.0,
    149.0,
    153.0,
    153.0,
    155.0,
    155.0,
    156.0,
    156.0,
    169.0,
    169.0,
    169.0,
    169.0,
    169.0
  ],
  "median_price": 149.0,
  "error": null
}